[
  {
    "eventId": "0503bcb0",
    "videoId": "74d5d2f0",
    "type": "detection",
    "location": "EDSA Sec Walk",
    "clockTime": "10:45:00 AM",
    "offsetSeconds": 0.0,
    "videoTime": "00:00:00",
    "pedestrianId": 3,
    "frame": 1,
    "occlusionClass": 0,
    "occlusionLabel": "light occlusion",
    "description": "Light occlusion pedestrian ID #3 detected at frame 1"
  },
  {
    "eventId": "28397691",
    "videoId": "74d5d2f0",
    "type": "detection",
    "location": "EDSA Sec Walk",
    "clockTime": "10:45:00 AM",
    "offsetSeconds": 0.0,
    "videoTime": "00:00:00",
    "pedestrianId": 1,
    "frame": 1,
    "occlusionClass": 0,
    "occlusionLabel": "light occlusion",
    "description": "Light occlusion pedestrian ID #1 detected at frame 1"
  },
  {
    "eventId": "30fdff63",
    "videoId": "74d5d2f0",
    "type": "detection",
    "location": "EDSA Sec Walk",
    "clockTime": "10:45:00 AM",
    "offsetSeconds": 0.0,
    "videoTime": "00:00:00",
    "pedestrianId": 5,
    "frame": 1,
    "occlusionClass": 1,
    "occlusionLabel": "moderate occlusion",
    "description": "Moderate occlusion pedestrian ID #5 detected at frame 1"
  },
  {
    "eventId": "3acd1b37",
    "videoId": "74d5d2f0",
    "type": "detection",
    "location": "EDSA Sec Walk",
    "clockTime": "10:45:00 AM",
    "offsetSeconds": 0.0,
    "videoTime": "00:00:00",
    "pedestrianId": 4,
    "frame": 1,
    "occlusionClass": 1,
    "occlusionLabel": "moderate occlusion",
    "description": "Moderate occlusion pedestrian ID #4 detected at frame 1"
  },
  {
    "eventId": "3f2c6485",
    "videoId": "74d5d2f0",
    "type": "detection",
    "location": "EDSA Sec Walk",
    "clockTime": "10:45:00 AM",
    "offsetSeconds": 0.0,
    "videoTime": "00:00:00",
    "pedestrianId": 2,
    "frame": 1,
    "occlusionClass": 0,
    "occlusionLabel": "light occlusion",
    "description": "Light occlusion pedestrian ID #2 detected at frame 1"
  },
  {
    "eventId": "515a9491",
    "videoId": "74d5d2f0",
    "type": "detection",
    "location": "EDSA Sec Walk",
    "clockTime": "10:45:00 AM",
    "offsetSeconds": 0.0,
    "videoTime": "00:00:00",
    "pedestrianId": 7,
    "frame": 1,
    "occlusionClass": 0,
    "occlusionLabel": "light occlusion",
    "description": "Light occlusion pedestrian ID #7 detected at frame 1"
  },
  {
    "eventId": "9aa440f4",
    "videoId": "74d5d2f0",
    "type": "detection",
    "location": "EDSA Sec Walk",
    "clockTime": "10:45:00 AM",
    "offsetSeconds": 0.0,
    "videoTime": "00:00:00",
    "pedestrianId": 6,
    "frame": 1,
    "occlusionClass": 0,
    "occlusionLabel": "light occlusion",
    "description": "Light occlusion pedestrian ID #6 detected at frame 1"
  },
  {
    "eventId": "c0ea014f",
    "videoId": "74d5d2f0",
    "type": "detection",
    "location": "EDSA Sec Walk",
    "clockTime": "10:45:00 AM",
    "offsetSeconds": 0.0,
    "videoTime": "00:00:00",
    "pedestrianId": 8,
    "frame": 1,
    "occlusionClass": 0,
    "occlusionLabel": "light occlusion",
    "description": "Light occlusion pedestrian ID #8 detected at frame 1"
  },
  {
    "eventId": "af4f9b45",
    "videoId": "74d5d2f0",
    "type": "detection",
    "location": "EDSA Sec Walk",
    "clockTime": "10:45:00 AM",
    "offsetSeconds": 0.27,
    "videoTime": "00:00:00",
    "pedestrianId": 11,
    "frame": 5,
    "occlusionClass": 0,
    "occlusionLabel": "light occlusion",
    "description": "Light occlusion pedestrian ID #11 detected at frame 5"
  },
  {
    "eventId": "dce86b66",
    "videoId": "74d5d2f0",
    "type": "detection",
    "location": "EDSA Sec Walk",
    "clockTime": "10:45:00 AM",
    "offsetSeconds": 0.27,
    "videoTime": "00:00:00",
    "pedestrianId": 10,
    "frame": 5,
    "occlusionClass": 0,
    "occlusionLabel": "light occlusion",
    "description": "Light occlusion pedestrian ID #10 detected at frame 5"
  },
  {
    "eventId": "e540e17d",
    "videoId": "74d5d2f0",
    "type": "detection",
    "location": "EDSA Sec Walk",
    "clockTime": "10:45:02 AM",
    "offsetSeconds": 2.6,
    "videoTime": "00:00:02",
    "pedestrianId": 16,
    "frame": 40,
    "occlusionClass": 0,
    "occlusionLabel": "light occlusion",
    "description": "Light occlusion pedestrian ID #16 detected at frame 40"
  },
  {
    "eventId": "0f833691",
    "videoId": "74d5d2f0",
    "type": "detection",
    "location": "EDSA Sec Walk",
    "clockTime": "10:45:03 AM",
    "offsetSeconds": 3.07,
    "videoTime": "00:00:03",
    "pedestrianId": 20,
    "frame": 47,
    "occlusionClass": 1,
    "occlusionLabel": "moderate occlusion",
    "description": "Moderate occlusion pedestrian ID #20 detected at frame 47"
  },
  {
    "eventId": "98c6bd72",
    "videoId": "74d5d2f0",
    "type": "detection",
    "location": "EDSA Sec Walk",
    "clockTime": "10:45:04 AM",
    "offsetSeconds": 4.8,
    "videoTime": "00:00:04",
    "pedestrianId": 24,
    "frame": 73,
    "occlusionClass": 1,
    "occlusionLabel": "moderate occlusion",
    "description": "Moderate occlusion pedestrian ID #24 detected at frame 73"
  },
  {
    "eventId": "99f67e70",
    "videoId": "74d5d2f0",
    "type": "detection",
    "location": "EDSA Sec Walk",
    "clockTime": "10:45:05 AM",
    "offsetSeconds": 5.4,
    "videoTime": "00:00:05",
    "pedestrianId": 31,
    "frame": 82,
    "occlusionClass": 0,
    "occlusionLabel": "light occlusion",
    "description": "Light occlusion pedestrian ID #31 detected at frame 82"
  },
  {
    "eventId": "5345e3ec",
    "videoId": "74d5d2f0",
    "type": "detection",
    "location": "EDSA Sec Walk",
    "clockTime": "10:45:06 AM",
    "offsetSeconds": 6.47,
    "videoTime": "00:00:06",
    "pedestrianId": 33,
    "frame": 98,
    "occlusionClass": 1,
    "occlusionLabel": "moderate occlusion",
    "description": "Moderate occlusion pedestrian ID #33 detected at frame 98"
  },
  {
    "eventId": "d6c8f2f8",
    "videoId": "74d5d2f0",
    "type": "detection",
    "location": "EDSA Sec Walk",
    "clockTime": "10:45:06 AM",
    "offsetSeconds": 6.47,
    "videoTime": "00:00:06",
    "pedestrianId": 32,
    "frame": 98,
    "occlusionClass": 1,
    "occlusionLabel": "moderate occlusion",
    "description": "Moderate occlusion pedestrian ID #32 detected at frame 98"
  },
  {
    "eventId": "af626b9f",
    "videoId": "74d5d2f0",
    "type": "detection",
    "location": "EDSA Sec Walk",
    "clockTime": "10:45:06 AM",
    "offsetSeconds": 6.8,
    "videoTime": "00:00:06",
    "pedestrianId": 39,
    "frame": 103,
    "occlusionClass": 0,
    "occlusionLabel": "light occlusion",
    "description": "Light occlusion pedestrian ID #39 detected at frame 103"
  },
  {
    "eventId": "7c34079f",
    "videoId": "74d5d2f0",
    "type": "detection",
    "location": "EDSA Sec Walk",
    "clockTime": "10:45:08 AM",
    "offsetSeconds": 8.33,
    "videoTime": "00:00:08",
    "pedestrianId": 42,
    "frame": 126,
    "occlusionClass": 1,
    "occlusionLabel": "moderate occlusion",
    "description": "Moderate occlusion pedestrian ID #42 detected at frame 126"
  },
  {
    "eventId": "ef64269d",
    "videoId": "74d5d2f0",
    "type": "detection",
    "location": "EDSA Sec Walk",
    "clockTime": "10:45:11 AM",
    "offsetSeconds": 11.07,
    "videoTime": "00:00:11",
    "pedestrianId": 46,
    "frame": 167,
    "occlusionClass": 0,
    "occlusionLabel": "light occlusion",
    "description": "Light occlusion pedestrian ID #46 detected at frame 167"
  },
  {
    "eventId": "633ad8e0",
    "videoId": "74d5d2f0",
    "type": "detection",
    "location": "EDSA Sec Walk",
    "clockTime": "10:45:12 AM",
    "offsetSeconds": 12.73,
    "videoTime": "00:00:12",
    "pedestrianId": 55,
    "frame": 192,
    "occlusionClass": 0,
    "occlusionLabel": "light occlusion",
    "description": "Light occlusion pedestrian ID #55 detected at frame 192"
  },
  {
    "eventId": "5f3dfd1f",
    "videoId": "74d5d2f0",
    "type": "detection",
    "location": "EDSA Sec Walk",
    "clockTime": "10:45:13 AM",
    "offsetSeconds": 13.4,
    "videoTime": "00:00:13",
    "pedestrianId": 59,
    "frame": 202,
    "occlusionClass": 1,
    "occlusionLabel": "moderate occlusion",
    "description": "Moderate occlusion pedestrian ID #59 detected at frame 202"
  },
  {
    "eventId": "19fe0551",
    "videoId": "74d5d2f0",
    "type": "detection",
    "location": "EDSA Sec Walk",
    "clockTime": "10:45:13 AM",
    "offsetSeconds": 13.67,
    "videoTime": "00:00:13",
    "pedestrianId": 61,
    "frame": 206,
    "occlusionClass": 1,
    "occlusionLabel": "moderate occlusion",
    "description": "Moderate occlusion pedestrian ID #61 detected at frame 206"
  },
  {
    "eventId": "d4d75ebf",
    "videoId": "74d5d2f0",
    "type": "detection",
    "location": "EDSA Sec Walk",
    "clockTime": "10:45:14 AM",
    "offsetSeconds": 14.07,
    "videoTime": "00:00:14",
    "pedestrianId": 64,
    "frame": 212,
    "occlusionClass": 0,
    "occlusionLabel": "light occlusion",
    "description": "Light occlusion pedestrian ID #64 detected at frame 212"
  },
  {
    "eventId": "dae04481",
    "videoId": "74d5d2f0",
    "type": "detection",
    "location": "EDSA Sec Walk",
    "clockTime": "10:45:14 AM",
    "offsetSeconds": 14.87,
    "videoTime": "00:00:14",
    "pedestrianId": 71,
    "frame": 224,
    "occlusionClass": 0,
    "occlusionLabel": "light occlusion",
    "description": "Light occlusion pedestrian ID #71 detected at frame 224"
  },
  {
    "eventId": "1f5183fa",
    "videoId": "74d5d2f0",
    "type": "detection",
    "location": "EDSA Sec Walk",
    "clockTime": "10:45:15 AM",
    "offsetSeconds": 15.27,
    "videoTime": "00:00:15",
    "pedestrianId": 74,
    "frame": 230,
    "occlusionClass": 1,
    "occlusionLabel": "moderate occlusion",
    "description": "Moderate occlusion pedestrian ID #74 detected at frame 230"
  },
  {
    "eventId": "2f5ccacb",
    "videoId": "74d5d2f0",
    "type": "detection",
    "location": "EDSA Sec Walk",
    "clockTime": "10:45:15 AM",
    "offsetSeconds": 15.27,
    "videoTime": "00:00:15",
    "pedestrianId": 73,
    "frame": 230,
    "occlusionClass": 1,
    "occlusionLabel": "moderate occlusion",
    "description": "Moderate occlusion pedestrian ID #73 detected at frame 230"
  },
  {
    "eventId": "2523bc8d",
    "videoId": "74d5d2f0",
    "type": "detection",
    "location": "EDSA Sec Walk",
    "clockTime": "10:45:15 AM",
    "offsetSeconds": 15.33,
    "videoTime": "00:00:15",
    "pedestrianId": 75,
    "frame": 231,
    "occlusionClass": 0,
    "occlusionLabel": "light occlusion",
    "description": "Light occlusion pedestrian ID #75 detected at frame 231"
  },
  {
    "eventId": "c0b88b9a",
    "videoId": "74d5d2f0",
    "type": "detection",
    "location": "EDSA Sec Walk",
    "clockTime": "10:45:15 AM",
    "offsetSeconds": 15.47,
    "videoTime": "00:00:15",
    "pedestrianId": 79,
    "frame": 233,
    "occlusionClass": 1,
    "occlusionLabel": "moderate occlusion",
    "description": "Moderate occlusion pedestrian ID #79 detected at frame 233"
  },
  {
    "eventId": "c7153daa",
    "videoId": "74d5d2f0",
    "type": "detection",
    "location": "EDSA Sec Walk",
    "clockTime": "10:45:15 AM",
    "offsetSeconds": 15.47,
    "videoTime": "00:00:15",
    "pedestrianId": 78,
    "frame": 233,
    "occlusionClass": 0,
    "occlusionLabel": "light occlusion",
    "description": "Light occlusion pedestrian ID #78 detected at frame 233"
  },
  {
    "eventId": "e9c7bf33",
    "videoId": "74d5d2f0",
    "type": "detection",
    "location": "EDSA Sec Walk",
    "clockTime": "10:45:16 AM",
    "offsetSeconds": 16.33,
    "videoTime": "00:00:16",
    "pedestrianId": 91,
    "frame": 246,
    "occlusionClass": 0,
    "occlusionLabel": "light occlusion",
    "description": "Light occlusion pedestrian ID #91 detected at frame 246"
  },
  {
    "eventId": "e94a9cb3",
    "videoId": "74d5d2f0",
    "type": "detection",
    "location": "EDSA Sec Walk",
    "clockTime": "10:45:17 AM",
    "offsetSeconds": 17.4,
    "videoTime": "00:00:17",
    "pedestrianId": 94,
    "frame": 262,
    "occlusionClass": 1,
    "occlusionLabel": "moderate occlusion",
    "description": "Moderate occlusion pedestrian ID #94 detected at frame 262"
  },
  {
    "eventId": "294fbfc2",
    "videoId": "74d5d2f0",
    "type": "detection",
    "location": "EDSA Sec Walk",
    "clockTime": "10:45:19 AM",
    "offsetSeconds": 19.13,
    "videoTime": "00:00:19",
    "pedestrianId": 103,
    "frame": 288,
    "occlusionClass": 0,
    "occlusionLabel": "light occlusion",
    "description": "Light occlusion pedestrian ID #103 detected at frame 288"
  },
  {
    "eventId": "11b63a61",
    "videoId": "74d5d2f0",
    "type": "detection",
    "location": "EDSA Sec Walk",
    "clockTime": "10:45:20 AM",
    "offsetSeconds": 20.6,
    "videoTime": "00:00:20",
    "pedestrianId": 109,
    "frame": 310,
    "occlusionClass": 0,
    "occlusionLabel": "light occlusion",
    "description": "Light occlusion pedestrian ID #109 detected at frame 310"
  },
  {
    "eventId": "81c2d9df",
    "videoId": "74d5d2f0",
    "type": "detection",
    "location": "EDSA Sec Walk",
    "clockTime": "10:45:23 AM",
    "offsetSeconds": 23.13,
    "videoTime": "00:00:23",
    "pedestrianId": 121,
    "frame": 348,
    "occlusionClass": 1,
    "occlusionLabel": "moderate occlusion",
    "description": "Moderate occlusion pedestrian ID #121 detected at frame 348"
  },
  {
    "eventId": "19eebe15",
    "videoId": "74d5d2f0",
    "type": "detection",
    "location": "EDSA Sec Walk",
    "clockTime": "10:45:23 AM",
    "offsetSeconds": 23.8,
    "videoTime": "00:00:23",
    "pedestrianId": 131,
    "frame": 358,
    "occlusionClass": 0,
    "occlusionLabel": "light occlusion",
    "description": "Light occlusion pedestrian ID #131 detected at frame 358"
  },
  {
    "eventId": "0c4f3b47",
    "videoId": "74d5d2f0",
    "type": "detection",
    "location": "EDSA Sec Walk",
    "clockTime": "10:45:23 AM",
    "offsetSeconds": 23.93,
    "videoTime": "00:00:23",
    "pedestrianId": 133,
    "frame": 360,
    "occlusionClass": 0,
    "occlusionLabel": "light occlusion",
    "description": "Light occlusion pedestrian ID #133 detected at frame 360"
  },
  {
    "eventId": "4a875970",
    "videoId": "74d5d2f0",
    "type": "detection",
    "location": "EDSA Sec Walk",
    "clockTime": "10:45:24 AM",
    "offsetSeconds": 24.47,
    "videoTime": "00:00:24",
    "pedestrianId": 138,
    "frame": 368,
    "occlusionClass": 1,
    "occlusionLabel": "moderate occlusion",
    "description": "Moderate occlusion pedestrian ID #138 detected at frame 368"
  },
  {
    "eventId": "e60b571c",
    "videoId": "74d5d2f0",
    "type": "detection",
    "location": "EDSA Sec Walk",
    "clockTime": "10:45:24 AM",
    "offsetSeconds": 24.8,
    "videoTime": "00:00:24",
    "pedestrianId": 142,
    "frame": 373,
    "occlusionClass": 0,
    "occlusionLabel": "light occlusion",
    "description": "Light occlusion pedestrian ID #142 detected at frame 373"
  },
  {
    "eventId": "8167f4ee",
    "videoId": "74d5d2f0",
    "type": "detection",
    "location": "EDSA Sec Walk",
    "clockTime": "10:45:25 AM",
    "offsetSeconds": 25.2,
    "videoTime": "00:00:25",
    "pedestrianId": 147,
    "frame": 379,
    "occlusionClass": 0,
    "occlusionLabel": "light occlusion",
    "description": "Light occlusion pedestrian ID #147 detected at frame 379"
  },
  {
    "eventId": "ebc6ea6b",
    "videoId": "74d5d2f0",
    "type": "detection",
    "location": "EDSA Sec Walk",
    "clockTime": "10:45:25 AM",
    "offsetSeconds": 25.4,
    "videoTime": "00:00:25",
    "pedestrianId": 154,
    "frame": 382,
    "occlusionClass": 1,
    "occlusionLabel": "moderate occlusion",
    "description": "Moderate occlusion pedestrian ID #154 detected at frame 382"
  },
  {
    "eventId": "6fccb240",
    "videoId": "74d5d2f0",
    "type": "detection",
    "location": "EDSA Sec Walk",
    "clockTime": "10:45:25 AM",
    "offsetSeconds": 25.6,
    "videoTime": "00:00:25",
    "pedestrianId": 162,
    "frame": 385,
    "occlusionClass": 1,
    "occlusionLabel": "moderate occlusion",
    "description": "Moderate occlusion pedestrian ID #162 detected at frame 385"
  },
  {
    "eventId": "05a65a19",
    "videoId": "74d5d2f0",
    "type": "detection",
    "location": "EDSA Sec Walk",
    "clockTime": "10:45:25 AM",
    "offsetSeconds": 25.67,
    "videoTime": "00:00:25",
    "pedestrianId": 164,
    "frame": 386,
    "occlusionClass": 0,
    "occlusionLabel": "light occlusion",
    "description": "Light occlusion pedestrian ID #164 detected at frame 386"
  },
  {
    "eventId": "071f5790",
    "videoId": "74d5d2f0",
    "type": "detection",
    "location": "EDSA Sec Walk",
    "clockTime": "10:45:25 AM",
    "offsetSeconds": 25.73,
    "videoTime": "00:00:25",
    "pedestrianId": 165,
    "frame": 387,
    "occlusionClass": 0,
    "occlusionLabel": "light occlusion",
    "description": "Light occlusion pedestrian ID #165 detected at frame 387"
  },
  {
    "eventId": "36e5f64e",
    "videoId": "74d5d2f0",
    "type": "detection",
    "location": "EDSA Sec Walk",
    "clockTime": "10:45:25 AM",
    "offsetSeconds": 25.87,
    "videoTime": "00:00:25",
    "pedestrianId": 166,
    "frame": 389,
    "occlusionClass": 0,
    "occlusionLabel": "light occlusion",
    "description": "Light occlusion pedestrian ID #166 detected at frame 389"
  },
  {
    "eventId": "5c8cbb12",
    "videoId": "74d5d2f0",
    "type": "detection",
    "location": "EDSA Sec Walk",
    "clockTime": "10:45:26 AM",
    "offsetSeconds": 26.87,
    "videoTime": "00:00:26",
    "pedestrianId": 173,
    "frame": 404,
    "occlusionClass": 1,
    "occlusionLabel": "moderate occlusion",
    "description": "Moderate occlusion pedestrian ID #173 detected at frame 404"
  },
  {
    "eventId": "c0e5017d",
    "videoId": "74d5d2f0",
    "type": "detection",
    "location": "EDSA Sec Walk",
    "clockTime": "10:45:27 AM",
    "offsetSeconds": 27.47,
    "videoTime": "00:00:27",
    "pedestrianId": 179,
    "frame": 413,
    "occlusionClass": 1,
    "occlusionLabel": "moderate occlusion",
    "description": "Moderate occlusion pedestrian ID #179 detected at frame 413"
  },
  {
    "eventId": "e16f94ae",
    "videoId": "74d5d2f0",
    "type": "detection",
    "location": "EDSA Sec Walk",
    "clockTime": "10:45:27 AM",
    "offsetSeconds": 27.67,
    "videoTime": "00:00:27",
    "pedestrianId": 180,
    "frame": 416,
    "occlusionClass": 1,
    "occlusionLabel": "moderate occlusion",
    "description": "Moderate occlusion pedestrian ID #180 detected at frame 416"
  },
  {
    "eventId": "a512f99e",
    "videoId": "74d5d2f0",
    "type": "detection",
    "location": "EDSA Sec Walk",
    "clockTime": "10:45:27 AM",
    "offsetSeconds": 27.87,
    "videoTime": "00:00:27",
    "pedestrianId": 181,
    "frame": 419,
    "occlusionClass": 0,
    "occlusionLabel": "light occlusion",
    "description": "Light occlusion pedestrian ID #181 detected at frame 419"
  },
  {
    "eventId": "7ec4b1d1",
    "videoId": "74d5d2f0",
    "type": "detection",
    "location": "EDSA Sec Walk",
    "clockTime": "10:45:28 AM",
    "offsetSeconds": 28.0,
    "videoTime": "00:00:28",
    "pedestrianId": 184,
    "frame": 421,
    "occlusionClass": 0,
    "occlusionLabel": "light occlusion",
    "description": "Light occlusion pedestrian ID #184 detected at frame 421"
  },
  {
    "eventId": "e0e4561f",
    "videoId": "74d5d2f0",
    "type": "detection",
    "location": "EDSA Sec Walk",
    "clockTime": "10:45:28 AM",
    "offsetSeconds": 28.07,
    "videoTime": "00:00:28",
    "pedestrianId": 186,
    "frame": 422,
    "occlusionClass": 0,
    "occlusionLabel": "light occlusion",
    "description": "Light occlusion pedestrian ID #186 detected at frame 422"
  }
]