[
  {
    "startOffsetSeconds": 0.0,
    "endOffsetSeconds": 1.792,
    "severity": "moderate",
    "score": 45.49
  },
  {
    "startOffsetSeconds": 1.792,
    "endOffsetSeconds": 5.375,
    "severity": "light",
    "score": 27.36
  },
  {
    "startOffsetSeconds": 5.375,
    "endOffsetSeconds": 8.958,
    "severity": "moderate",
    "score": 38.96
  },
  {
    "startOffsetSeconds": 8.958,
    "endOffsetSeconds": 10.75,
    "severity": "light",
    "score": 29.35
  },
  {
    "startOffsetSeconds": 10.75,
    "endOffsetSeconds": 14.333,
    "severity": "moderate",
    "score": 44.25
  },
  {
    "startOffsetSeconds": 14.333,
    "endOffsetSeconds": 16.125,
    "severity": "light",
    "score": 22.52
  },
  {
    "startOffsetSeconds": 16.125,
    "endOffsetSeconds": 25.083,
    "severity": "moderate",
    "score": 42.14
  },
  {
    "startOffsetSeconds": 25.083,
    "endOffsetSeconds": 34.042,
    "severity": "light",
    "score": 25.62
  },
  {
    "startOffsetSeconds": 34.042,
    "endOffsetSeconds": 35.833,
    "severity": "neutral",
    "score": null
  },
  {
    "startOffsetSeconds": 35.833,
    "endOffsetSeconds": 37.625,
    "severity": "light",
    "score": 17.08
  },
  {
    "startOffsetSeconds": 37.625,
    "endOffsetSeconds": 39.417,
    "severity": "neutral",
    "score": null
  },
  {
    "startOffsetSeconds": 39.417,
    "endOffsetSeconds": 43.0,
    "severity": "light",
    "score": 26.21
  }
]